{
  "name": "player_item_break",
  "description": "プレイヤにアイテムを破壊させます。",
  "base": "player_$base",
  "arguments": {
    "item": {
      "description": "壊れたアイテムです。",
      "$ref": "#/definitions/itemStack"
    },
    "slot": {
      "description": "壊れたアイテムが入っていたスロットです。",
      "$ref": "#/definitions/itemSlot"
    }
  },
  "outputs": {
    "item": {
      "description": "壊れたアイテムです。",
      "$ref": "#/definitions/itemStack"
    },
    "slot": {
      "description": "壊れたアイテムが入っていたスロットです。",
      "$ref": "#/definitions/itemSlot"
    }
  }
}
